pyproject_creator/__init__.py
pyproject_creator/cli.py
pyproject_creator/template/.cz.toml
pyproject_creator/template/.gitignore
pyproject_creator/template/.pre-commit-config.yaml
pyproject_creator/template/github_action/workflows/bumpversion.yml
pyproject_creator/template/github_action/workflows/pythonpublish.yml
pyproject_creator/template/github_action/workflows/test.yml
pyproject_creator/template/logs/__init__.py
pyproject_creator/template/logs/_default.py
pyproject_creator/template/pyproject.template
pyproject_creator/template/scripts/__init__.py
pyproject_creator/template/scripts/commit_with_pre_commit.py
pyproject_creator/template/tests/__init__.py
pyproject_creator/template/tests/test_sample.py
pyproject_creator-0.4.1.dist-info/LICENSE
pyproject_creator-0.4.1.dist-info/METADATA
pyproject_creator-0.4.1.dist-info/WHEEL
pyproject_creator-0.4.1.dist-info/entry_points.txt
pyproject_creator-0.4.1.dist-info/RECORD
