Metadata-Version: 2.1
Name: pyproject-creator
Version: 0.4.1
Summary: A tool to create Python project templates
Home-page: https://github.com/atiasn/pyproject-creator
License: MIT
Keywords: packaging,pyproject-creator
Author: NextKele
Author-email: ritboylei@gmail.com
Requires-Python: >=3.11,<4.0
Classifier: License :: OSI Approved :: MIT License
Classifier: Programming Language :: Python :: 3
Classifier: Programming Language :: Python :: 3.11
Classifier: Programming Language :: Python :: 3.12
Requires-Dist: click (>=8.1.7,<9.0.0)
Requires-Dist: jinja2 (>=3.1.4,<4.0.0)
Project-URL: Repository, https://github.com/atiasn/pyproject-creator
